{"ProjectName": "GamyFi Platform","ShortDescription": "GamyFi platform is a fantasy sports platform and NFT","Description": "GamyFi platform is a fantasy sports platform and NFT marketplace supporting all ERC721 NFT tokens.","LogoName": "gamyfi.jpg","Website": "https://gamyfi.org/home","Twitter": "https://twitter.com/GamyFi_HQ","Telegram": "https://t.me/GamyFi_ANN","Discord": "https://discord.gg/4Zq5QzBKHS","Blog": "https://gamyfi.medium.com/","Github": "https://gitlab.com/gamyfiteam","Other": "https://www.coingecko.com/en/coins/gamyfi-token","Category": "NFT"} 
